{
  "project_info": {
    "project_number": "482878912904",
    "firebase_url": "https://momo-mahjong-app.firebaseio.com",
    "project_id": "momo-mahjong-app",
    "storage_bucket": "momo-mahjong-app.appspot.com"
  },
  "client": [
    {
      "client_info": {
        "mobilesdk_app_id": "1:482878912904:android:01efa90d100fb08a",
        "android_client_info": {
          "package_name": "momonyan.mahjongg_tools"
        }
      },
      "oauth_client": [
        {
          "client_id": "482878912904-ekakqnhhprplqc2ja92jjog897l74l54.apps.googleusercontent.com",
          "client_type": 1,
          "android_info": {
            "package_name": "momonyan.mahjongg_tools",
            "certificate_hash": "76c37af5142f9c4fede2013d12a2194d4da262ad"
          }
        },
        {
          "client_id": "482878912904-r1fj06op5re9a6hac53dlbo9jtkfd9ks.apps.googleusercontent.com",
          "client_type": 3
        }
      ],
      "api_key": [
        {
          "current_key": "AIzaSyA2HigMfYv8m9Suzy7PmrLWe01POVCW3FY"
        }
      ],
      "services": {
        "appinvite_service": {
          "other_platform_oauth_client": [
            {
              "client_id": "482878912904-r1fj06op5re9a6hac53dlbo9jtkfd9ks.apps.googleusercontent.com",
              "client_type": 3
            }
          ]
        }
      },
      "admob_app_id": "ca-app-pub-6499097800180510~1231013049"
    }
  ],
  "configuration_version": "1"
}